aiogram_sentinel/__init__.py
aiogram_sentinel/config.py
aiogram_sentinel/context.py
aiogram_sentinel/decorators.py
aiogram_sentinel/errors.py
aiogram_sentinel/events.py
aiogram_sentinel/exceptions.py
aiogram_sentinel/policy.py
aiogram_sentinel/scopes.py
aiogram_sentinel/sentinel.py
aiogram_sentinel/types.py
aiogram_sentinel/version.py
aiogram_sentinel/integrations/__init__.py
aiogram_sentinel/integrations/sentry.py
aiogram_sentinel/middlewares/__init__.py
aiogram_sentinel/middlewares/debouncing.py
aiogram_sentinel/middlewares/errors.py
aiogram_sentinel/middlewares/policy_resolver.py
aiogram_sentinel/middlewares/throttling.py
aiogram_sentinel/storage/__init__.py
aiogram_sentinel/storage/base.py
aiogram_sentinel/storage/factory.py
aiogram_sentinel/storage/memory.py
aiogram_sentinel/storage/redis.py
aiogram_sentinel/utils/__init__.py
aiogram_sentinel/utils/keys.py
aiogram_sentinel-1.1.0.dist-info/METADATA
aiogram_sentinel-1.1.0.dist-info/WHEEL
aiogram_sentinel-1.1.0.dist-info/licenses/LICENSE
aiogram_sentinel-1.1.0.dist-info/RECORD
