Metadata-Version: 2.4
Name: aiogram-sentinel
Version: 1.1.0
Summary: Edge hygiene library for aiogram v3 with middlewares, router, and storage backends
Project-URL: Homepage, https://github.com/aiogram-sentinel/aiogram-sentinel
Project-URL: Repository, https://github.com/aiogram-sentinel/aiogram-sentinel
Project-URL: Issues, https://github.com/aiogram-sentinel/aiogram-sentinel/issues
Author: aiogram-sentinel contributors
License: MIT
License-File: LICENSE
Classifier: Development Status :: 3 - Alpha
Classifier: Intended Audience :: Developers
Classifier: License :: OSI Approved :: MIT License
Classifier: Operating System :: OS Independent
Classifier: Programming Language :: Python :: 3
Classifier: Programming Language :: Python :: 3.10
Classifier: Programming Language :: Python :: 3.11
Classifier: Programming Language :: Python :: 3.12
Classifier: Programming Language :: Python :: 3.13
Classifier: Topic :: Communications :: Chat
Classifier: Topic :: Software Development :: Libraries :: Python Modules
Requires-Python: >=3.10
Requires-Dist: aiogram>=3.0.0
Requires-Dist: redis>=4.0.0
Provides-Extra: dev
Requires-Dist: bandit>=1.7.0; extra == 'dev'
Requires-Dist: black>=23.0.0; extra == 'dev'
Requires-Dist: build>=1.0.0; extra == 'dev'
Requires-Dist: isort>=5.12.0; extra == 'dev'
Requires-Dist: pip-audit>=2.0.0; extra == 'dev'
Requires-Dist: pyright>=1.1.0; extra == 'dev'
Requires-Dist: pytest-asyncio>=0.21.0; extra == 'dev'
Requires-Dist: pytest-benchmark>=4.0.0; extra == 'dev'
Requires-Dist: pytest-cov>=4.0.0; extra == 'dev'
Requires-Dist: pytest-mock>=3.10.0; extra == 'dev'
Requires-Dist: pytest>=7.0.0; extra == 'dev'
Requires-Dist: ruff>=0.1.0; extra == 'dev'
Requires-Dist: twine>=5.0.0; extra == 'dev'
Provides-Extra: redis
Requires-Dist: redis>=5.0; extra == 'redis'
Provides-Extra: sentry
Requires-Dist: sentry-sdk>=1.40.0; extra == 'sentry'
